molweightcal/__init__.py
molweightcal/molecule.py
molweightcal-0.1.0.dist-info/License
molweightcal-0.1.0.dist-info/METADATA
molweightcal-0.1.0.dist-info/WHEEL
molweightcal-0.1.0.dist-info/top_level.txt
molweightcal-0.1.0.dist-info/RECORD
