Metadata-Version: 2.1
Name: molweightcal
Version: 0.1.0
Summary: A lightweight package to calculate molecular weights from chemical formulas.
Author: Md. Ismiel Hossen Abir
Author-email: ismielabir1971@gmail.com
Classifier: Programming Language :: Python :: 3
Classifier: Intended Audience :: Science/Research
Classifier: License :: OSI Approved :: MIT License
Classifier: Topic :: Scientific/Engineering :: Chemistry
Classifier: Operating System :: OS Independent
Requires-Python: >=3.6
License-File: License
